msquaredc/__init__.py
msquaredc/__main__.py
msquaredc/cli.py
msquaredc/command.py
msquaredc/persistence.py
msquaredc/project.py
msquaredc/utils.py
msquaredc/ui/__init__.py
msquaredc/ui/interfaces.py
msquaredc/ui/gui/__init__.py
msquaredc/ui/gui/coding_unit.py
msquaredc/ui/gui/core.py
msquaredc/ui/gui/dialogs.py
msquaredc/ui/gui/frame.py
msquaredc/ui/gui/menu.py
msquaredc/ui/gui/presenter.py
msquaredc/ui/gui/widgets.py
msquaredc/ui/tui/__init__.py
msquaredc/ui/tui/presenter.py
msquaredc-0.1.1.281.dist-info/AUTHORS.rst
msquaredc-0.1.1.281.dist-info/LICENSE
msquaredc-0.1.1.281.dist-info/METADATA
msquaredc-0.1.1.281.dist-info/WHEEL
msquaredc-0.1.1.281.dist-info/entry_points.txt
msquaredc-0.1.1.281.dist-info/top_level.txt
msquaredc-0.1.1.281.dist-info/RECORD
