Metadata-Version: 2.1
Name: msquaredc
Version: 0.1.1.281
Summary: A Tool for more independent data coding.
Home-page: https://github.com/j340m3/python-msquaredc
Author: Jerome Bergmann
Author-email: bergmann.jerome@gmail.com
License: BSD
Platform: UNKNOWN
Classifier: Development Status :: 1 - Planning
Classifier: Intended Audience :: Developers
Classifier: License :: OSI Approved :: BSD License
Classifier: Operating System :: Unix
Classifier: Operating System :: POSIX
Classifier: Operating System :: Microsoft :: Windows
Classifier: Programming Language :: Python
Classifier: Programming Language :: Python :: 2.7
Classifier: Programming Language :: Python :: 3
Classifier: Programming Language :: Python :: 3.3
Classifier: Programming Language :: Python :: 3.4
Classifier: Programming Language :: Python :: 3.5
Classifier: Programming Language :: Python :: 3.6
Classifier: Programming Language :: Python :: Implementation :: CPython
Classifier: Topic :: Utilities
Requires-Dist: click
Requires-Dist: PyYAML
Requires-Dist: urwid
Requires-Dist: six
Requires-Dist: future
Requires-Dist: SQLAlchemy
